filewire/__init__.py
filewire/filewire.py
filewire/recv.py
filewire/send.py
filewire-0.0.10.dist-info/DESCRIPTION.rst
filewire-0.0.10.dist-info/METADATA
filewire-0.0.10.dist-info/RECORD
filewire-0.0.10.dist-info/WHEEL
filewire-0.0.10.dist-info/entry_points.txt
filewire-0.0.10.dist-info/metadata.json
filewire-0.0.10.dist-info/top_level.txt
