Metadata-Version: 2.0
Name: filewire
Version: 0.0.10
Summary: Easily send and receive files over LAN
Home-page: https://github.com/zxey/filewire
Author: zxey
Author-email: zxey.bones@gmail.com
License: MIT
Keywords: lan share send receive file
Platform: UNKNOWN
Classifier: Development Status :: 3 - Alpha
Classifier: Environment :: Console
Classifier: Natural Language :: English
Classifier: Intended Audience :: End Users/Desktop
Classifier: License :: OSI Approved :: MIT License
Classifier: Programming Language :: Python :: 3.4
Classifier: Programming Language :: Python :: 3.5
Classifier: Operating System :: OS Independent
Classifier: Topic :: Communications
Classifier: Topic :: Internet
